tailucas_pylib/__init__.py
tailucas_pylib/app.py
tailucas_pylib/aws/__init__.py
tailucas_pylib/aws/metrics.py
tailucas_pylib/bluetooth.py
tailucas_pylib/creds.py
tailucas_pylib/data.py
tailucas_pylib/datetime.py
tailucas_pylib/device.py
tailucas_pylib/flags.py
tailucas_pylib/handler.py
tailucas_pylib/process.py
tailucas_pylib/rabbit.py
tailucas_pylib/threads.py
tailucas_pylib/tools/__init__.py
tailucas_pylib/tools/aws_configure.py
tailucas_pylib/tools/config_interpol.py
tailucas_pylib/tools/cred_tool.py
tailucas_pylib/tools/yaml_interpol.py
tailucas_pylib/zmq.py
tailucas_pylib-0.6.1.dist-info/WHEEL
tailucas_pylib-0.6.1.dist-info/entry_points.txt
tailucas_pylib-0.6.1.dist-info/METADATA
tailucas_pylib-0.6.1.dist-info/RECORD
