Metadata-Version: 2.3
Name: tailucas-pylib
Version: 0.6.1
Summary: Add your description here
Requires-Dist: boto3>=1.40.21
Requires-Dist: cronitor>=4.7.1
Requires-Dist: onepassword-sdk>=0.3.1
Requires-Dist: onepasswordconnectsdk>=1.5.1
Requires-Dist: pika>=1.3.2
Requires-Dist: pydantic>=2.11.7
Requires-Dist: python-dateutil>=2.9.0.post0
Requires-Dist: pytz>=2025.2
Requires-Dist: pyyaml>=6.0.2
Requires-Dist: pyzmq>=27.0.2
Requires-Dist: sentry-sdk>=2.35.1
Requires-Dist: simplejson>=3.20.1
Requires-Dist: u-msgpack-python>=2.8.0
Requires-Python: >=3.11
